nleis/__init__.py
nleis/data_processing.py
nleis/fitting.py
nleis/nleis.py
nleis/nleis_elements_pair.py
nleis/nleis_fitting.py
nleis/parallel.py
nleis/validation.py
nleis/visualization.py
nleis/data/Z1s_30a.txt
nleis/data/Z2s_30a.txt
nleis/data/autolab_100mA.txt
nleis/data/autolab_25mA.txt
nleis/data/autolab_50mA.txt
nleis/data/freq_30a.txt
nleis/tests/__init__.py
nleis/tests/test_data_processing.py
nleis/tests/test_graph.py
nleis/tests/test_model_io.py
nleis/tests/test_nleis.py
nleis/tests/test_nleis_elements_pair.py
nleis/tests/test_nleis_fitting.py
nleis/tests/test_parallel.py
nleis/tests/test_validation.py
nleis/tests/test_visualization.py
nleis-0.3.dist-info/licenses/LICENSE
nleis-0.3.dist-info/METADATA
nleis-0.3.dist-info/WHEEL
nleis-0.3.dist-info/top_level.txt
nleis-0.3.dist-info/RECORD
