Metadata-Version: 2.4
Name: nleis
Version: 0.3
Summary: A NLEIS toolbox for impedance.py that provides RC level nonlinear equivalent circuit modeling (nECM) and analysis
Home-page: https://nleispy.readthedocs.io/en/latest/
Author: Yuefan Ji and nleis.py developers
Author-email: yuefan@uw.edu
Project-URL: Bug Tracker, https://github.com/yuefan98/nleis.py
Classifier: Programming Language :: Python :: 3
Classifier: License :: OSI Approved :: MIT License
Classifier: Operating System :: OS Independent
Requires-Python: >=3.8,<3.14
License-File: LICENSE
Requires-Dist: altair>=3.0
Requires-Dist: matplotlib>=3.5
Requires-Dist: numpy>=1.14
Requires-Dist: scipy>=1.0
Requires-Dist: networkx>=2.6.3
Requires-Dist: impedance>=1.7.1
Requires-Dist: pandas>=2.0.2
Requires-Dist: threadpoolctl>=3.5.0
Requires-Dist: joblib>=1.4.2
Requires-Dist: SALib>=1.4.8
Requires-Dist: tqdm>=4.66.5
Dynamic: author
Dynamic: author-email
Dynamic: classifier
Dynamic: description
Dynamic: description-content-type
Dynamic: home-page
Dynamic: license-file
Dynamic: project-url
Dynamic: requires-dist
Dynamic: requires-python
Dynamic: summary
